LICENSE
README.md
pyproject.toml
setup.py
hashflow/__init__.py
hashflow/api.py
hashflow/helpers/__init__.py
hashflow/helpers/chains.py
hashflow/helpers/common.py
hashflow/helpers/exceptions.py
hashflow/helpers/validation.py
hashflow_taker_sdk.egg-info/PKG-INFO
hashflow_taker_sdk.egg-info/SOURCES.txt
hashflow_taker_sdk.egg-info/dependency_links.txt
hashflow_taker_sdk.egg-info/requires.txt
hashflow_taker_sdk.egg-info/top_level.txt
tests/__init__.py
tests/test_api.py