Metadata-Version: 2.1
Name: hashflow-taker-sdk
Version: 1.0.0
Summary: Python SDK to interact with the Hashflow Taker API
Author: Hashflow Foundation
Author-email: Sameer Brenn <sameer@hashflow.com>, Victor Ionescu <victor@hashflow.com>
Project-URL: Homepage, https://github.com/hashflownetwork/taker-py
Keywords: hashflow exchange api defi ethereum eth
Classifier: Programming Language :: Python :: 3
Classifier: License :: OSI Approved :: MIT License
Classifier: Operating System :: OS Independent
Requires-Python: >=3.7
License-File: LICENSE
